[
    {
        "id": 1,
        "title": "Home",
        "slug": "home",
        "body": "Here is some lame body content for testing purposes.  Here is some lame body content for testing purposes.  Here is some lame body content for testing purposes."
    },
    {
        "id": 2,
        "title": "Services",
        "slug": "services",
        "body": "Here is some lame body content for testing purposes.  Here is some lame body content for testing purposes.  Here is some lame body content for testing purposes."
    },
    {
        "id": 3,
        "title": "Contact Us",
        "slug": "contact",
        "body": "Here is some lame body content for testing purposes.  Here is some lame body content for testing purposes.  Here is some lame body content for testing purposes."
    }
    {
        "id": 4,
        "title": "About",
        "slug": "about",
        "body": "Here is some lame body content for testing purposes.  Here is some lame body content for testing purposes.  Here is some lame body content for testing purposes."
    },
]